llama_index/llms/mlx/__init__.py
llama_index/llms/mlx/base.py
llama_index/llms/mlx/tokenizer_utils.py
llama_index/llms/mlx/utils.py
llama_index_llms_mlx-0.4.1.dist-info/METADATA
llama_index_llms_mlx-0.4.1.dist-info/WHEEL
llama_index_llms_mlx-0.4.1.dist-info/licenses/LICENSE
llama_index_llms_mlx-0.4.1.dist-info/RECORD
