Metadata-Version: 2.4
Name: llama-index-llms-mlx
Version: 0.4.1
Summary: llama-index llms mlx integration
Author-email: Dwight Foster <dwightfoster03@gmail.com>
License-Expression: MIT
License-File: LICENSE
Requires-Python: <4.0,>=3.9
Requires-Dist: llama-index-core<0.15,>=0.13.0
Requires-Dist: mlx-lm>=0.11.0
Requires-Dist: mlx>=0.11.0
